execode/__init__.py
execode/entry_points_console_scripts.py
execode/env.py
execode/finder.py
execode/pyinfo.py
execode/runner.py
execode/utils.py
execode-0.1.2.dist-info/LICENSE
execode-0.1.2.dist-info/METADATA
execode-0.1.2.dist-info/WHEEL
execode-0.1.2.dist-info/entry_points.txt
execode-0.1.2.dist-info/top_level.txt
execode-0.1.2.dist-info/RECORD
