Metadata-Version: 2.1
Name: execode
Version: 0.1.2
Summary: UNKNOWN
Home-page: https://github.com/Cologler/execode-python
License: MIT License
Platform: UNKNOWN
Classifier: License :: OSI Approved :: MIT License
Classifier: Programming Language :: Python :: 3.7
Requires-Dist: fsoopify
